README.md
setup.cfg
setup.py
ucanSystec/__init__.py
ucanSystec/ucanSystec.py
ucanSystec.egg-info/PKG-INFO
ucanSystec.egg-info/SOURCES.txt
ucanSystec.egg-info/dependency_links.txt
ucanSystec.egg-info/top_level.txt