Metadata-Version: 1.1
Name: ucanSystec
Version: 0.2.2
Summary: Systec usb/can dll bindings
Home-page: https://github.com/SMFSW/python-ucanSystec
Author: SMFSW
Author-email: xgarmanboziax@gmail.com
License: MIT
Keywords: Communication,CAN,Systec,DLL
Platform: UNKNOWN
Classifier: License :: OSI Approved :: MIT License
Classifier: Development Status :: 5 - Production/Stable
Classifier: Intended Audience :: Developers
Classifier: Topic :: Utilities
Classifier: Natural Language :: English
Classifier: Programming Language :: Python :: 2
Classifier: Programming Language :: Python :: 3
